build/lib/build/lib/oelint_data/__init__.py
build/lib/oelint_data/__init__.py
oelint_data/__init__.py
oelint_data/fallback/core.json
oelint_data/kirkstone/clang-layer.json
oelint_data/kirkstone/core.json
oelint_data/kirkstone/filesystems-layer.json
oelint_data/kirkstone/flutter-layer.json
oelint_data/kirkstone/freescale-distro.json
oelint_data/kirkstone/freescale-layer.json
oelint_data/kirkstone/gnome-layer.json
oelint_data/kirkstone/intel.json
oelint_data/kirkstone/meta-initramfs.json
oelint_data/kirkstone/meta-python.json
oelint_data/kirkstone/meta-sca.json
oelint_data/kirkstone/multimedia-layer.json
oelint_data/kirkstone/networking-layer.json
oelint_data/kirkstone/openembedded-layer.json
oelint_data/kirkstone/perl-layer.json
oelint_data/kirkstone/qt6-layer.json
oelint_data/kirkstone/rubygems.json
oelint_data/kirkstone/virtualization-layer.json
oelint_data/kirkstone/webkit.json
oelint_data/kirkstone/webserver.json
oelint_data/kirkstone/xfce-layer.json
oelint_data/kirkstone/yocto.json
oelint_data/kirkstone/yoctobsp.json
oelint_data/langdale/clang-layer.json
oelint_data/langdale/core.json
oelint_data/langdale/filesystems-layer.json
oelint_data/langdale/freescale-distro.json
oelint_data/langdale/freescale-layer.json
oelint_data/langdale/gnome-layer.json
oelint_data/langdale/intel.json
oelint_data/langdale/meta-initramfs.json
oelint_data/langdale/meta-python.json
oelint_data/langdale/meta-sca.json
oelint_data/langdale/multimedia-layer.json
oelint_data/langdale/networking-layer.json
oelint_data/langdale/openembedded-layer.json
oelint_data/langdale/perl-layer.json
oelint_data/langdale/qt6-layer.json
oelint_data/langdale/rubygems.json
oelint_data/langdale/virtualization-layer.json
oelint_data/langdale/webkit.json
oelint_data/langdale/webserver.json
oelint_data/langdale/xfce-layer.json
oelint_data/langdale/yocto.json
oelint_data/langdale/yoctobsp.json
oelint_data/mickledore/clang-layer.json
oelint_data/mickledore/core.json
oelint_data/mickledore/filesystems-layer.json
oelint_data-1.3.6.dist-info/licenses/LICENSE
oelint_data-1.3.6.dist-info/METADATA
oelint_data-1.3.6.dist-info/WHEEL
oelint_data-1.3.6.dist-info/top_level.txt
oelint_data-1.3.6.dist-info/RECORD
