Metadata-Version: 2.4
Name: oelint_data
Version: 1.3.6
Summary: Data for oelint-adv
Maintainer-email: Konrad Weihmann <kweihmann@outlook.com>
License-Expression: BSD-2-Clause
Project-URL: homepage, https://github.com/priv-kweihmann/oelint-data
Project-URL: repository, https://github.com/priv-kweihmann/oelint-data.git
Project-URL: bugtracker, https://github.com/priv-kweihmann/oelint-data/issues
Project-URL: documentation, https://github.com/priv-kweihmann/oelint-adv/blob/master/docs/constants.md
Classifier: Development Status :: 5 - Production/Stable
Classifier: Environment :: Console
Classifier: Intended Audience :: Developers
Classifier: Natural Language :: English
Classifier: Operating System :: POSIX :: Linux
Classifier: Programming Language :: Python :: 3 :: Only
Classifier: Programming Language :: Python :: 3
Classifier: Programming Language :: Python :: 3.10
Classifier: Programming Language :: Python :: 3.11
Classifier: Programming Language :: Python :: 3.12
Classifier: Programming Language :: Python :: 3.13
Classifier: Programming Language :: Python :: 3.14
Classifier: Topic :: Software Development :: Quality Assurance
Requires-Python: >=3.10
License-File: LICENSE
Requires-Dist: oelint-parser~=8.5
Provides-Extra: dev
Requires-Dist: bump-my-version==1.2.6; extra == "dev"
Requires-Dist: build~=1.4; extra == "dev"
Requires-Dist: kas~=5.1; extra == "dev"
Requires-Dist: oelint-adv~=9.3; extra == "dev"
Requires-Dist: twine==6.2.0; extra == "dev"
Requires-Dist: wheel~=0.46; extra == "dev"
Dynamic: license-file
